base_files/Dockerfile.txt
base_files/app.main.txt
base_files/app.run.txt
base_files/build-docker.txt
base_files/env.txt
base_files/pkg.__init__.txt
base_files/pkg.config.txt
base_files/pkg.postgres.orm.txt
base_files/pkg.postgres.postgres_client.txt
base_files/requirements.txt
postgres_fastapi_boilerplate/__init__.py
postgres_fastapi_boilerplate/__main__.py
postgres_fastapi_boilerplate-1.0.1.dist-info/LICENSE
postgres_fastapi_boilerplate-1.0.1.dist-info/METADATA
postgres_fastapi_boilerplate-1.0.1.dist-info/WHEEL
postgres_fastapi_boilerplate-1.0.1.dist-info/top_level.txt
postgres_fastapi_boilerplate-1.0.1.dist-info/RECORD
