Metadata-Version: 2.1
Name: postgres-fastapi-boilerplate
Version: 1.0.1
Summary: Basic boilerplate providing a postgres client and FastAPI app.
Author: Josh Minneti
License: Permission is hereby granted, free of charge, to any person obtaining a copy of this software and associated documentation files (the “Software”), to deal in the Software without restriction, including without limitation the rights to use, copy, modify, merge, publish, distribute, sublicense, and/or sell copies of the Software, and to permit persons to whom the Software is furnished to do so, subject to the following conditions:
Keywords: postgres,fastapi,boilerplate
Classifier: License :: OSI Approved :: MIT License
Classifier: Programming Language :: Python
Classifier: Programming Language :: Python :: 3
Requires-Python: >=3.10
License-File: LICENSE
